quark_tsp/__init__.py
quark_tsp/classical_tsp_solver.py
quark_tsp/tsp_graph_provider.py
quark_tsp/tsp_qubo_mapping_dnx.py
quark_tsp-0.1.1.dist-info/METADATA
quark_tsp-0.1.1.dist-info/WHEEL
quark_tsp-0.1.1.dist-info/top_level.txt
quark_tsp-0.1.1.dist-info/RECORD
