Metadata-Version: 2.2
Name: quark-tsp
Version: 0.1.1
Summary: Tsp plugin for the quark framework
Author-email: Philipp Ross <philipp.ross@bmw.de>, Marvin Erdmann <marvin.erdmann@bmw.de>, Andre Luckow <andre.luckow@bmwgroup.com>, Greshma Shaji <greshma.shaji@bmwgroup.com>, Florian Kiwit <florian.kiwit@bmw.de>, Benjamin Decker <benjamin.decker@bmw.de>
License: Apache-2.0
Classifier: Programming Language :: Python :: 3
Classifier: Operating System :: OS Independent
Requires-Python: >=3.12
Requires-Dist: dwave-networkx>=0.8.16
Requires-Dist: networkx>=3.4.2
Requires-Dist: numpy>=2.2.3
Requires-Dist: quark-framework>=0.1.3
